setup.py
ZhiTools.egg-info/PKG-INFO
ZhiTools.egg-info/SOURCES.txt
ZhiTools.egg-info/dependency_links.txt
ZhiTools.egg-info/requires.txt
ZhiTools.egg-info/top_level.txt
simpletest/__init__.py
simpletest/test.py