Metadata-Version: 1.0
Name: ZhiTools
Version: 0.0.1
Summary: just a simple test
Home-page: UNKNOWN
Author: zli
Author-email: lizhicq@hotmail.com
License: MIT License
Keywords: simple,test
Platform: any
